py_auth0_jwt-0.3.0.dist-info/METADATA
py_auth0_jwt-0.3.0.dist-info/RECORD
py_auth0_jwt-0.3.0.dist-info/WHEEL
py_auth0_jwt-0.3.0.dist-info/top_level.txt
pyauth0jwt/__init__.py
pyauth0jwt/auth0authenticate.py
pyauth0jwt/settings.py
